retrivex/__init__.py
retrivex/adapters/__init__.py
retrivex/core/__init__.py
retrivex/core/models.py
retrivex/core/retriever.py
retrivex/eval/__init__.py
retrivex/utils/__init__.py
retrivex/utils/chunking.py
retrivexlib-0.1.0.dist-info/licenses/LICENSE
retrivexlib-0.1.0.dist-info/METADATA
retrivexlib-0.1.0.dist-info/WHEEL
retrivexlib-0.1.0.dist-info/entry_points.txt
retrivexlib-0.1.0.dist-info/top_level.txt
retrivexlib-0.1.0.dist-info/RECORD
