Metadata-Version: 2.4
Name: retrivexlib
Version: 0.1.0
Summary: Lightweight neighbor-expansion retriever for addressing LLM positional bias in long contexts
Author-email: Sushanth Reddy <sushanthdondapati5@gmail.com>
Maintainer-email: Sushanth Reddy <sushanthdondapati5@gmail.com>
License-Expression: MIT
Project-URL: Homepage, https://github.com/Sushanth-reddyD/retrivex
Project-URL: Repository, https://github.com/Sushanth-reddyD/retrivex
Project-URL: Issues, https://github.com/Sushanth-reddyD/retrivex/issues
Project-URL: Documentation, https://github.com/Sushanth-reddyD/retrivex/blob/main/README.md
Project-URL: Changelog, https://github.com/Sushanth-reddyD/retrivex/blob/main/CHANGELOG.md
Keywords: retrieval,rag,llm,vector-search,context-window,positional-bias,neighbor-expansion
Classifier: Development Status :: 4 - Beta
Classifier: Intended Audience :: Developers
Classifier: Intended Audience :: Science/Research
Classifier: Topic :: Scientific/Engineering :: Artificial Intelligence
Classifier: Topic :: Software Development :: Libraries :: Python Modules
Classifier: Topic :: Text Processing :: Indexing
Classifier: Programming Language :: Python :: 3
Classifier: Programming Language :: Python :: 3.10
Classifier: Programming Language :: Python :: 3.11
Classifier: Programming Language :: Python :: 3.12
Classifier: Operating System :: OS Independent
Requires-Python: >=3.10
License-File: LICENSE
Requires-Dist: numpy>=1.24.0
Requires-Dist: pydantic>=2.0.0
Provides-Extra: langchain
Requires-Dist: langchain>=0.1.0; extra == "langchain"
Requires-Dist: langchain-core>=0.1.0; extra == "langchain"
Provides-Extra: llamaindex
Requires-Dist: llama-index>=0.9.0; extra == "llamaindex"
Provides-Extra: eval
Requires-Dist: scikit-learn>=1.3.0; extra == "eval"
Requires-Dist: pandas>=2.0.0; extra == "eval"
Requires-Dist: matplotlib>=3.7.0; extra == "eval"
Provides-Extra: dev
Requires-Dist: pytest>=7.4.0; extra == "dev"
Requires-Dist: pytest-cov>=4.1.0; extra == "dev"
Requires-Dist: black>=23.0.0; extra == "dev"
Requires-Dist: ruff>=0.1.0; extra == "dev"
Requires-Dist: mypy>=1.5.0; extra == "dev"
Provides-Extra: all
Requires-Dist: retrivex[dev,eval,langchain,llamaindex]; extra == "all"
Dynamic: license-file
